szh_toolbox/__init__.py
szh_toolbox/commond.py
szh_toolbox/instrument_frequency.py
szh_toolbox/mylogger.py
szh_toolbox/namelist.py
szh_toolbox/namelist_wps.py
szh_toolbox/namelist_wps_ui.py
szh_toolbox/noaa_download.py
szh_toolbox/test123.py
szh_toolbox-0.0.18.dist-info/entry_points.txt
szh_toolbox-0.0.18.dist-info/WHEEL
szh_toolbox-0.0.18.dist-info/METADATA
szh_toolbox-0.0.18.dist-info/RECORD
