Metadata-Version: 2.1
Name: szh_toolbox
Version: 0.0.18
Summary: 我自己的工具箱
Author-email: szh <suo.zh@qq.com>
Requires-Python: >=3.7
Classifier: Programming Language :: Python :: 3
Classifier: License :: OSI Approved :: MIT License
Classifier: Operating System :: OS Independent
Project-URL: Bug Tracker, https://github.com/pypa/sampleproject/issues
Project-URL: Homepage, https://github.com/pypa/sampleproject
